odoo/addons/fs_image_thumbnail/README.rst
odoo/addons/fs_image_thumbnail/__init__.py
odoo/addons/fs_image_thumbnail/__manifest__.py
odoo/addons/fs_image_thumbnail/i18n/es.po
odoo/addons/fs_image_thumbnail/i18n/fs_image_thumbnail.pot
odoo/addons/fs_image_thumbnail/i18n/it.po
odoo/addons/fs_image_thumbnail/models/__init__.py
odoo/addons/fs_image_thumbnail/models/fs_image_thumbnail_mixin.py
odoo/addons/fs_image_thumbnail/models/fs_thumbnail.py
odoo/addons/fs_image_thumbnail/models/ir_attachment.py
odoo/addons/fs_image_thumbnail/readme/CONTEXT.md
odoo/addons/fs_image_thumbnail/readme/CONTRIBUTORS.md
odoo/addons/fs_image_thumbnail/readme/CREDITS.md
odoo/addons/fs_image_thumbnail/readme/DESCRIPTION.md
odoo/addons/fs_image_thumbnail/readme/HISTORY.md
odoo/addons/fs_image_thumbnail/readme/USAGE.md
odoo/addons/fs_image_thumbnail/readme/newsfragments/.gitignore
odoo/addons/fs_image_thumbnail/security/fs_thumbnail.xml
odoo/addons/fs_image_thumbnail/static/description/icon.png
odoo/addons/fs_image_thumbnail/static/description/index.html
odoo/addons/fs_image_thumbnail/tests/__init__.py
odoo/addons/fs_image_thumbnail/tests/test_fs_image_thumbnail.py
odoo/addons/fs_image_thumbnail/views/fs_image_thumbnail_mixin.xml
odoo/addons/fs_image_thumbnail/views/fs_thumbnail.xml
odoo/addons/fs_image_thumbnail/views/ir_attachment.xml
odoo_addon_fs_image_thumbnail-17.0.1.0.0.3.dist-info/METADATA
odoo_addon_fs_image_thumbnail-17.0.1.0.0.3.dist-info/WHEEL
odoo_addon_fs_image_thumbnail-17.0.1.0.0.3.dist-info/top_level.txt
odoo_addon_fs_image_thumbnail-17.0.1.0.0.3.dist-info/RECORD
